python_cath/__init__.py
python_cath/__main__.py
python_cath/concat.py
python_cath/example.py
python_cath/py.typed
python_cath-0.2.5.dist-info/entry_points.txt
python_cath-0.2.5.dist-info/LICENSE
python_cath-0.2.5.dist-info/WHEEL
python_cath-0.2.5.dist-info/METADATA
python_cath-0.2.5.dist-info/RECORD
