Metadata-Version: 2.1
Name: python-cath
Version: 0.2.5
Summary: Cat files w/ headers
Home-page: https://github.com/samesense/python-cath
License: MIT
Author: samesense
Author-email: candptea@gmail.com
Requires-Python: >=3.7,<4.0
Classifier: Development Status :: 3 - Alpha
Classifier: Intended Audience :: Developers
Classifier: License :: OSI Approved :: MIT License
Classifier: Operating System :: OS Independent
Classifier: Programming Language :: Python :: 3
Classifier: Programming Language :: Python :: 3.7
Classifier: Programming Language :: Python :: 3.8
Classifier: Topic :: Software Development :: Libraries :: Python Modules
Requires-Dist: importlib_metadata (>=1.6.0,<2.0.0); python_version < "3.8"
Requires-Dist: pre-commit (>=2.5.1,<3.0.0)
Requires-Dist: rich (>=2.2.2,<3.0.0)
Requires-Dist: typer[all] (>=0.2.1,<0.3.0)
Project-URL: Repository, https://github.com/samesense/python-cath
